{
    "NON_ENG": {
        "0": "als",
        "1": "I",
        "2": "zijn",
        "3": "dat",
        "4": "hij",
        "5": "was",
        "6": "voor",
        "7": "op",
        "8": "zijn",
        "9": "met",
        "10": "ze",
        "11": "zijn",
        "12": "bij",
        "13": "een",
        "14": "hebben",
        "15": "deze",
        "16": "van",
        "17": "door",
        "18": "heet",
        "19": "woord",
        "20": "maar",
        "21": "wat",
        "22": "sommige",
        "23": "is",
        "24": "het",
        "25": "u",
        "26": "of",
        "27": "had",
        "28": "de",
        "29": "van",
        "30": "aan",
        "31": "en",
        "32": "een",
        "33": "in",
        "34": "we",
        "35": "kan",
        "36": "uit",
        "37": "andere",
        "38": "waren",
        "39": "die",
        "40": "doen",
        "41": "hun",
        "42": "tijd",
        "43": "indien",
        "44": "zal",
        "45": "hoe",
        "46": "zei",
        "47": "een",
        "48": "elk",
        "49": "vertellen",
        "50": "doet",
        "51": "set",
        "52": "drie",
        "53": "willen",
        "54": "lucht",
        "55": "goed",
        "56": "ook",
        "57": "spelen",
        "58": "klein",
        "59": "end",
        "60": "zetten",
        "61": "thuis",
        "62": "lezen",
        "63": "de hand",
        "64": "poort",
        "65": "grote",
        "66": "spell",
        "67": "toevoegen",
        "68": "zelfs",
        "69": "land",
        "70": "hier",
        "71": "moet",
        "72": "grote",
        "73": "hoog",
        "74": "dergelijke",
        "75": "volgen",
        "76": "act",
        "77": "waarom",
        "78": "vragen",
        "79": "mannen",
        "80": "verandering",
        "81": "ging",
        "82": "licht",
        "83": "soort",
        "84": "uitgeschakeld",
        "85": "nodig hebben",
        "86": "huis",
        "87": "afbeelding",
        "88": "proberen",
        "89": "ons",
        "90": "weer",
        "91": "dier",
        "92": "punt",
        "93": "moeder",
        "94": "wereld",
        "95": "dichtbij",
        "96": "bouwen",
        "97": "zelf",
        "98": "aarde",
        "99": "vader",
        "100": "een",
        "101": "nieuwe",
        "102": "werk",
        "103": "deel",
        "104": "nemen",
        "105": "krijgen",
        "106": "plaats",
        "107": "gemaakt",
        "108": "wonen",
        "109": "waar",
        "110": "na",
        "111": "terug",
        "112": "weinig",
        "113": "alleen",
        "114": "ronde",
        "115": "man",
        "116": "jaar",
        "117": "kwam",
        "118": "Show",
        "119": "elke",
        "120": "goed",
        "121": "mij",
        "122": "geven",
        "123": "onze",
        "124": "onder",
        "125": "naam",
        "126": "zeer",
        "127": "door",
        "128": "gewoon",
        "129": "vorm",
        "130": "zin",
        "131": "grote",
        "132": "denken",
        "133": "zeggen",
        "134": "helpen",
        "135": "laag",
        "136": "lijn",
        "137": "verschillen",
        "138": "beurt",
        "139": "oorzaak",
        "140": "veel",
        "141": "betekenen",
        "142": "voor",
        "143": "verhuizing",
        "144": "rechts",
        "145": "jongen",
        "146": "oude",
        "147": "ook",
        "148": "hetzelfde",
        "149": "ze",
        "150": "alle",
        "151": "er",
        "152": "wanneer",
        "153": "omhoog",
        "154": "gebruiken",
        "155": "uw",
        "156": "manier",
        "157": "over",
        "158": "veel",
        "159": "dan",
        "160": "hen",
        "161": "schrijven",
        "162": "zou",
        "163": "zoals",
        "164": "dus",
        "165": "deze",
        "166": "haar",
        "167": "lang",
        "168": "maken",
        "169": "ding",
        "170": "zien",
        "171": "hem",
        "172": "twee",
        "173": "heeft",
        "174": "kijken",
        "175": "meer",
        "176": "dag",
        "177": "kon",
        "178": "gaan",
        "179": "komen",
        "180": "deed",
        "181": "aantal",
        "182": "klinken",
        "183": "geen",
        "184": "meest",
        "185": "mensen",
        "186": "mijn",
        "187": "meer dan",
        "188": "weten",
        "189": "water",
        "190": "dan",
        "191": "roep",
        "192": "eerste",
        "193": "die",
        "194": "kan",
        "195": "naar beneden",
        "196": "kant",
        "197": "geweest",
        "198": "nu",
        "199": "vinden",
        "200": "hoofd",
        "201": "staan",
        "202": "eigen",
        "203": "pagina",
        "204": "moeten",
        "205": "land",
        "206": "gevonden",
        "207": "antwoord",
        "208": "de school",
        "209": "groeien",
        "210": "studie",
        "211": "nog",
        "212": "leren",
        "213": "planten",
        "214": "afdekking",
        "215": "voedsel",
        "216": "zon",
        "217": "vier",
        "218": "tussen",
        "219": "staat",
        "220": "houden",
        "221": "oog",
        "222": "nooit",
        "223": "laatste",
        "224": "laten",
        "225": "gedachte",
        "226": "stad",
        "227": "boom",
        "228": "oversteken",
        "229": "boerderij",
        "230": "hard",
        "231": "begin",
        "232": "zou",
        "233": "verhaal",
        "234": "zaag",
        "235": "ver",
        "236": "zee",
        "237": "tekenen",
        "238": "links",
        "239": "laat",
        "240": "lopen",
        "241": "niet",
        "242": "terwijl",
        "243": "pers",
        "244": "dicht",
        "245": "nacht",
        "246": "echt",
        "247": "leven",
        "248": "weinig",
        "249": "noorden",
        "250": "boek",
        "251": "dragen",
        "252": "nam",
        "253": "wetenschap",
        "254": "eet",
        "255": "kamer",
        "256": "vriend",
        "257": "begon",
        "258": "idee",
        "259": "vis",
        "260": "berg",
        "261": "stop",
        "262": "eenmaal",
        "263": "base",
        "264": "hear",
        "265": "paard",
        "266": "gesneden",
        "267": "zeker",
        "268": "kijken",
        "269": "kleur",
        "270": "gezicht",
        "271": "hout",
        "272": "belangrijkste",
        "273": "geopend",
        "274": "lijken",
        "275": "samen",
        "276": "volgende",
        "277": "wit",
        "278": "kinderen",
        "279": "beginnen",
        "280": "kreeg",
        "281": "lopen",
        "282": "voorbeeld",
        "283": "gemak",
        "284": "papier",
        "285": "groep",
        "286": "altijd",
        "287": "muziek",
        "288": "die",
        "289": "beide",
        "290": "mark",
        "291": "vaak",
        "292": "brief",
        "293": "tot",
        "294": "mijl",
        "295": "rivier",
        "296": "auto",
        "297": "voeten",
        "298": "zorg",
        "299": "tweede",
        "300": "genoeg",
        "301": "vlakte",
        "302": "meisje",
        "303": "gebruikelijke",
        "304": "jonge",
        "305": "klaar",
        "306": "boven",
        "307": "ooit",
        "308": "rood",
        "309": "lijst",
        "310": "hoewel",
        "311": "voelen",
        "312": "Overleg",
        "313": "vogel",
        "314": "spoedig",
        "315": "lichaam",
        "316": "hond",
        "317": "familie",
        "318": "rechtstreeks",
        "319": "pose",
        "320": "vertrekken",
        "321": "lied",
        "322": "meten",
        "323": "deur",
        "324": "artikel",
        "325": "zwart",
        "326": "korte",
        "327": "cijfer",
        "328": "klasse",
        "329": "wind",
        "330": "vraag",
        "331": "gebeuren",
        "332": "compleet",
        "333": "schip",
        "334": "gebied",
        "335": "helft",
        "336": "rots",
        "337": "orde",
        "338": "brand",
        "339": "zuiden",
        "340": "probleem",
        "341": "stuk",
        "342": "vertelde",
        "343": "wist",
        "344": "passeren",
        "345": "sinds",
        "346": "boven",
        "347": "geheel",
        "348": "king",
        "349": "straat",
        "350": "inch",
        "351": "vermenigvuldigen",
        "352": "niets",
        "353": "cursus",
        "354": "blijven",
        "355": "wiel",
        "356": "volledige",
        "357": "kracht",
        "358": "blauw",
        "359": "object",
        "360": "beslissen",
        "361": "oppervlak",
        "362": "diepe",
        "363": "maan",
        "364": "eiland",
        "365": "voet",
        "366": "systeem",
        "367": "drukke",
        "368": "toets",
        "369": "opnemen",
        "370": "boot",
        "371": "gemeenschappelijke",
        "372": "goud",
        "373": "mogelijk",
        "374": "vliegtuig",
        "375": "plaats",
        "376": "droge",
        "377": "afvragen",
        "378": "lachen",
        "379": "duizend",
        "380": "geleden",
        "381": "ran",
        "382": "controleren",
        "383": "spel",
        "384": "vorm",
        "385": "gelijk",
        "386": "heet",
        "387": "miss",
        "388": "bracht",
        "389": "warmte",
        "390": "sneeuw",
        "391": "band",
        "392": "brengen",
        "393": "ja",
        "394": "verre",
        "395": "vullen",
        "396": "oosten",
        "397": "schilderen",
        "398": "taal",
        "399": "onder",
        "400": "eenheid",
        "401": "kracht",
        "402": "stad",
        "403": "fijne",
        "404": "bepaalde",
        "405": "vliegen",
        "406": "vallen",
        "407": "leiden",
        "408": "huilen",
        "409": "donker",
        "410": "apparaat",
        "411": "noot",
        "412": "wachten",
        "413": "plannen",
        "414": "figuur",
        "415": "ster",
        "416": "doos",
        "417": "zelfstandig naamwoord",
        "418": "veld",
        "419": "rest",
        "420": "juist",
        "421": "in staat",
        "422": "pond",
        "423": "gedaan",
        "424": "schoonheid",
        "425": "rijden",
        "426": "stond",
        "427": "bevatten",
        "428": "voorzijde",
        "429": "leren",
        "430": "week",
        "431": "finale",
        "432": "gaf",
        "433": "groen",
        "434": "oh",
        "435": "snel",
        "436": "ontwikkelen",
        "437": "oceaan",
        "438": "warme",
        "439": "gratis",
        "440": "minuut",
        "441": "sterke",
        "442": "speciaal",
        "443": "geest",
        "444": "achter",
        "445": "duidelijk",
        "446": "staart",
        "447": "produceren",
        "448": "feit",
        "449": "ruimte",
        "450": "gehoord",
        "451": "best",
        "452": "uur",
        "453": "beter",
        "454": "ware",
        "455": "tijdens",
        "456": "honderd",
        "457": "vijf",
        "458": "onthouden",
        "459": "stap",
        "460": "vroeg",
        "461": "houden",
        "462": "west",
        "463": "grond",
        "464": "rente",
        "465": "bereiken",
        "466": "snel",
        "467": "werkwoord",
        "468": "zingen",
        "469": "luisteren",
        "470": "zes",
        "471": "tafel",
        "472": "reizen",
        "473": "minder",
        "474": "ochtend",
        "475": "tien",
        "476": "eenvoudig",
        "477": "verscheidene",
        "478": "klinker",
        "479": "in de richting van",
        "480": "oorlog",
        "481": "leggen",
        "482": "tegen",
        "483": "patroon",
        "484": "langzaam",
        "485": "centrum",
        "486": "liefde",
        "487": "persoon",
        "488": "geld",
        "489": "dienen",
        "490": "verschijnen",
        "491": "weg",
        "492": "kaart",
        "493": "regen",
        "494": "regel",
        "495": "regeren",
        "496": "trek",
        "497": "koude",
        "498": "kennisgeving",
        "499": "stem",
        "500": "energie",
        "501": "hunt",
        "502": "waarschijnlijk",
        "503": "bedden",
        "504": "broer",
        "505": "ei",
        "506": "rit",
        "507": "cel",
        "508": "geloven",
        "509": "misschien",
        "510": "pick",
        "511": "plotseling",
        "512": "tellen",
        "513": "square",
        "514": "reden",
        "515": "lengte",
        "516": "vertegenwoordigen",
        "517": "kunst",
        "518": "onderwerp",
        "519": "regio",
        "520": "grootte",
        "521": "vari\u00ebren",
        "522": "vestigen",
        "523": "spreken",
        "524": "gewicht",
        "525": "algemeen",
        "526": "ijs",
        "527": "aangelegenheid",
        "528": "cirkel",
        "529": "paar",
        "530": "omvatten",
        "531": "kloof",
        "532": "lettergreep",
        "533": "vilt",
        "534": "grand",
        "535": "bal",
        "536": "nog",
        "537": "wave",
        "538": "laten vallen",
        "539": "hart",
        "540": "ben",
        "541": "aanwezig",
        "542": "zwaar",
        "543": "dans",
        "544": "motor",
        "545": "positie",
        "546": "arm",
        "547": "breed",
        "548": "zeil",
        "549": "materiaal",
        "550": "fractie",
        "551": "bos",
        "552": "zitten",
        "553": "ras",
        "554": "venster",
        "555": "winkel",
        "556": "zomer",
        "557": "trein",
        "558": "slaap",
        "559": "bewijzen",
        "560": "eenzame",
        "561": "been",
        "562": "oefening",
        "563": "muur",
        "564": "vangst",
        "565": "berg",
        "566": "wensen",
        "567": "hemel",
        "568": "boord",
        "569": "vreugde",
        "570": "de winter",
        "571": "zat",
        "572": "geschreven",
        "573": "wild",
        "574": "instrument",
        "575": "gehouden",
        "576": "glas",
        "577": "gras",
        "578": "koe",
        "579": "werk",
        "580": "edge",
        "581": "teken",
        "582": "bezoek",
        "583": "verleden",
        "584": "zachte",
        "585": "lol",
        "586": "heldere",
        "587": "gas",
        "588": "weer",
        "589": "maand",
        "590": "miljoen",
        "591": "dragen",
        "592": "afwerking",
        "593": "happy",
        "594": "hopen",
        "595": "bloem",
        "596": "kleden",
        "597": "vreemd",
        "598": "weg",
        "599": "handel",
        "600": "melodie",
        "601": "reis",
        "602": "kantoor",
        "603": "ontvangen",
        "604": "rij",
        "605": "mond",
        "606": "exacte",
        "607": "symbool",
        "608": "sterven",
        "609": "minste",
        "610": "problemen",
        "611": "schreeuw",
        "612": "behalve",
        "613": "schreef",
        "614": "zaad",
        "615": "toon",
        "616": "toetreden tot",
        "617": "suggereren",
        "618": "schoon",
        "619": "break",
        "620": "dame",
        "621": "yard",
        "622": "stijgen",
        "623": "slecht",
        "624": "klap",
        "625": "olie",
        "626": "bloed",
        "627": "aanraken",
        "628": "groeide",
        "629": "procent",
        "630": "mengen",
        "631": "team",
        "632": "draad",
        "633": "kosten",
        "634": "verloren",
        "635": "bruin",
        "636": "dragen",
        "637": "tuin",
        "638": "gelijk",
        "639": "verzonden",
        "640": "kiezen",
        "641": "viel",
        "642": "passen",
        "643": "stromen",
        "644": "eerlijk",
        "645": "bank",
        "646": "verzamelen",
        "647": "besparen",
        "648": "controle",
        "649": "decimaal",
        "650": "oor",
        "651": "anders",
        "652": "heel",
        "653": "brak",
        "654": "geval",
        "655": "midden",
        "656": "doden",
        "657": "zoon",
        "658": "meer",
        "659": "momenteel",
        "660": "schaal",
        "661": "luid",
        "662": "voorjaar",
        "663": "waarnemen",
        "664": "kind",
        "665": "straight",
        "666": "medeklinker",
        "667": "natie",
        "668": "woordenboek",
        "669": "melk",
        "670": "snelheid",
        "671": "methode",
        "672": "orgel",
        "673": "betalen",
        "674": "leeftijd",
        "675": "sectie",
        "676": "kleding",
        "677": "wolk",
        "678": "verrassing",
        "679": "rustig",
        "680": "steen",
        "681": "minuscuul",
        "682": "klimmen",
        "683": "koele",
        "684": "ontwerp",
        "685": "slechte",
        "686": "veel",
        "687": "experiment",
        "688": "onderzijde",
        "689": "sleutel",
        "690": "ijzer",
        "691": "enkelvoudige",
        "692": "stok",
        "693": "flat",
        "694": "twintig",
        "695": "huid",
        "696": "glimlach",
        "697": "vouw",
        "698": "gat",
        "699": "springen",
        "700": "kindje",
        "701": "acht",
        "702": "dorp",
        "703": "ontmoeten",
        "704": "wortel",
        "705": "kopen",
        "706": "verhogen",
        "707": "op te lossen",
        "708": "metalen",
        "709": "of",
        "710": "duw",
        "711": "zeven",
        "712": "paragraaf",
        "713": "derde",
        "714": "zal",
        "715": "gehouden",
        "716": "haar",
        "717": "beschrijven",
        "718": "kok",
        "719": "vloer",
        "720": "ofwel",
        "721": "resultaat",
        "722": "verbranden",
        "723": "hill",
        "724": "veilig",
        "725": "kat",
        "726": "eeuw",
        "727": "overwegen",
        "728": "soort",
        "729": "wet",
        "730": "beetje",
        "731": "kust",
        "732": "kopie",
        "733": "zinsnede",
        "734": "stil",
        "735": "hoog",
        "736": "zand",
        "737": "bodem",
        "738": "rol",
        "739": "temperatuur",
        "740": "vinger",
        "741": "industrie",
        "742": "waarde",
        "743": "strijd",
        "744": "leugen",
        "745": "verslaan",
        "746": "excite",
        "747": "natuurlijke",
        "748": "view",
        "749": "sense",
        "750": "hoofdstad",
        "751": "zal niet",
        "752": "stoel",
        "753": "gevaar",
        "754": "fruit",
        "755": "rijk",
        "756": "dikke",
        "757": "soldaat",
        "758": "proces",
        "759": "werken",
        "760": "praktijk",
        "761": "apart",
        "762": "moeilijk",
        "763": "arts",
        "764": "aub",
        "765": "beschermen",
        "766": "middag",
        "767": "gewas",
        "768": "moderne",
        "769": "onderdeel",
        "770": "hit",
        "771": "leerling",
        "772": "hoek",
        "773": "partij",
        "774": "levering",
        "775": "wiens",
        "776": "lokaliseren",
        "777": "kookplaten",
        "778": "karakter",
        "779": "insecten",
        "780": "gevangen",
        "781": "periode",
        "782": "geven",
        "783": "radio In",
        "784": "sprak",
        "785": "atoom",
        "786": "menselijk",
        "787": "geschiedenis",
        "788": "werking",
        "789": "elektrische",
        "790": "verwachten",
        "791": "bot",
        "792": "spoor",
        "793": "stel",
        "794": "bieden",
        "795": "instemmen",
        "796": "dus",
        "797": "zachte",
        "798": "vrouw",
        "799": "kapitein",
        "800": "denk",
        "801": "noodzakelijk",
        "802": "scherpe",
        "803": "vleugel",
        "804": "cre\u00ebren",
        "805": "buurman",
        "806": "wassen",
        "807": "vleermuis",
        "808": "eerder",
        "809": "menigte",
        "810": "ma\u00efs",
        "811": "vergelijken",
        "812": "gedicht",
        "813": "koord",
        "814": "bell",
        "815": "afhangen",
        "816": "vlees",
        "817": "wrijven",
        "818": "buis",
        "819": "beroemde",
        "820": "deas",
        "821": "stroom",
        "822": "angst",
        "823": "zicht",
        "824": "dun",
        "825": "driehoek",
        "826": "planeet",
        "827": "haast",
        "828": "chief",
        "829": "kolonie",
        "830": "klok",
        "831": "de mijne",
        "832": "stropdas",
        "833": "voeren",
        "834": "grote",
        "835": "vers",
        "836": "zoeken",
        "837": "sturen",
        "838": "geel",
        "839": "pistool",
        "840": "toelaten",
        "841": "afdrukken",
        "842": "dood",
        "843": "plek",
        "844": "woestijn",
        "845": "pak",
        "846": "huidige",
        "847": "lift",
        "848": "gestegen",
        "849": "aankomen",
        "850": "meester",
        "851": "spoor",
        "852": "ouder",
        "853": "oever",
        "854": "divisie",
        "855": "blad",
        "856": "stof",
        "857": "gunst",
        "858": "aansluiten",
        "859": "post",
        "860": "besteden",
        "861": "akkoord",
        "862": "vet",
        "863": "blij",
        "864": "origineel",
        "865": "aandeel",
        "866": "station",
        "867": "dad",
        "868": "brood",
        "869": "rekenen",
        "870": "behoorlijk",
        "871": "bar",
        "872": "aanbod",
        "873": "segmenten",
        "874": "slaaf",
        "875": "eend",
        "876": "onmiddellijke",
        "877": "markt",
        "878": "graad",
        "879": "bevolken",
        "880": "kuiken",
        "881": "lieve",
        "882": "vijand",
        "883": "antwoorden",
        "884": "drankje",
        "885": "voorkomen",
        "886": "ondersteuning",
        "887": "spraak",
        "888": "natuur",
        "889": "reeks",
        "890": "stoom",
        "891": "beweging",
        "892": "pad",
        "893": "vloeistof",
        "894": "aanmelden",
        "895": "betekende",
        "896": "quoti\u00ebnt",
        "897": "tanden",
        "898": "schelp",
        "899": "nek",
        "900": "zuurstof",
        "901": "suiker",
        "902": "dood",
        "903": "vrij",
        "904": "vaardigheid",
        "905": "vrouwen",
        "906": "seizoen",
        "907": "oplossing",
        "908": "magneet",
        "909": "zilver",
        "910": "dank",
        "911": "tak",
        "912": "wedstrijd",
        "913": "achtervoegsel",
        "914": "vooral",
        "915": "vijg",
        "916": "bang",
        "917": "reusachtig",
        "918": "zus",
        "919": "staal",
        "920": "bespreken",
        "921": "vooruit",
        "922": "gelijkaardige",
        "923": "begeleiden",
        "924": "ervaring",
        "925": "partituur",
        "926": "appel",
        "927": "gekocht",
        "928": "geleid",
        "929": "toonhoogte",
        "930": "coat",
        "931": "massa",
        "932": "kaart",
        "933": "band",
        "934": "touw",
        "935": "slip",
        "936": "win",
        "937": "dromen",
        "938": "avond",
        "939": "voorwaarde",
        "940": "voer",
        "941": "gereedschap",
        "942": "totaal",
        "943": "elementaire",
        "944": "geur",
        "945": "dal",
        "946": "noch",
        "947": "dubbel",
        "948": "zitje",
        "949": "blijven",
        "950": "blokkeren",
        "951": "grafiek",
        "952": "hoed",
        "953": "verkopen",
        "954": "succes",
        "955": "bedrijf",
        "956": "aftrekken",
        "957": "evenement",
        "958": "bijzonder",
        "959": "deal",
        "960": "zwemmen",
        "961": "termijn",
        "962": "tegengesteld",
        "963": "vrouw",
        "964": "schoen",
        "965": "schouder",
        "966": "spreiding",
        "967": "regelen",
        "968": "kamp",
        "969": "uitvinden",
        "970": "katoen",
        "971": "geboren",
        "972": "bepalen",
        "973": "quart",
        "974": "negen",
        "975": "vrachtwagen",
        "976": "geluidsoverlast",
        "977": "niveau",
        "978": "kans",
        "979": "verzamelen",
        "980": "winkel",
        "981": "rekken",
        "982": "gooien",
        "983": "glans",
        "984": "pand",
        "985": "column",
        "986": "molecuul",
        "987": "selecteren",
        "988": "mis",
        "989": "grijs",
        "990": "herhaal",
        "991": "vereisen",
        "992": "brede",
        "993": "bereiden",
        "994": "zout",
        "995": "neus",
        "996": "meervoud",
        "997": "woede",
        "998": "vordering",
        "999": "werelddeel",
        "1000": NaN,
        "1001": NaN
    },
    "ENG": {
        "0": "as",
        "1": "I",
        "2": "his",
        "3": "that",
        "4": "he",
        "5": "was",
        "6": "for",
        "7": "on",
        "8": "are",
        "9": "with",
        "10": "they",
        "11": "be",
        "12": "at",
        "13": "one",
        "14": "have",
        "15": "this",
        "16": "from",
        "17": "by",
        "18": "hot",
        "19": "word",
        "20": "but",
        "21": "what",
        "22": "some",
        "23": "is",
        "24": "it",
        "25": "you",
        "26": "or",
        "27": "had",
        "28": "the",
        "29": "of",
        "30": "to",
        "31": "and",
        "32": "a",
        "33": "in",
        "34": "we",
        "35": "can",
        "36": "out",
        "37": "other",
        "38": "were",
        "39": "which",
        "40": "do",
        "41": "their",
        "42": "time",
        "43": "if",
        "44": "will",
        "45": "how",
        "46": "said",
        "47": "an",
        "48": "each",
        "49": "tell",
        "50": "does",
        "51": "set",
        "52": "three",
        "53": "want",
        "54": "air",
        "55": "well",
        "56": "also",
        "57": "play",
        "58": "small",
        "59": "end",
        "60": "put",
        "61": "home",
        "62": "read",
        "63": "hand",
        "64": "port",
        "65": "large",
        "66": "spell",
        "67": "add",
        "68": "even",
        "69": "land",
        "70": "here",
        "71": "must",
        "72": "big",
        "73": "high",
        "74": "such",
        "75": "follow",
        "76": "act",
        "77": "why",
        "78": "ask",
        "79": "men",
        "80": "change",
        "81": "went",
        "82": "light",
        "83": "kind",
        "84": "off",
        "85": "need",
        "86": "house",
        "87": "picture",
        "88": "try",
        "89": "us",
        "90": "again",
        "91": "animal",
        "92": "point",
        "93": "mother",
        "94": "world",
        "95": "near",
        "96": "build",
        "97": "self",
        "98": "earth",
        "99": "father",
        "100": "any",
        "101": "new",
        "102": "work",
        "103": "part",
        "104": "take",
        "105": "get",
        "106": "place",
        "107": "made",
        "108": "live",
        "109": "where",
        "110": "after",
        "111": "back",
        "112": "little",
        "113": "only",
        "114": "round",
        "115": "man",
        "116": "year",
        "117": "came",
        "118": "show",
        "119": "every",
        "120": "good",
        "121": "me",
        "122": "give",
        "123": "our",
        "124": "under",
        "125": "name",
        "126": "very",
        "127": "through",
        "128": "just",
        "129": "form",
        "130": "sentence",
        "131": "great",
        "132": "think",
        "133": "say",
        "134": "help",
        "135": "low",
        "136": "line",
        "137": "differ",
        "138": "turn",
        "139": "cause",
        "140": "much",
        "141": "mean",
        "142": "before",
        "143": "move",
        "144": "right",
        "145": "boy",
        "146": "old",
        "147": "too",
        "148": "same",
        "149": "she",
        "150": "all",
        "151": "there",
        "152": "when",
        "153": "up",
        "154": "use",
        "155": "your",
        "156": "way",
        "157": "about",
        "158": "many",
        "159": "then",
        "160": "them",
        "161": "write",
        "162": "would",
        "163": "like",
        "164": "so",
        "165": "these",
        "166": "her",
        "167": "long",
        "168": "make",
        "169": "thing",
        "170": "see",
        "171": "him",
        "172": "two",
        "173": "has",
        "174": "look",
        "175": "more",
        "176": "day",
        "177": "could",
        "178": "go",
        "179": "come",
        "180": "did",
        "181": "number",
        "182": "sound",
        "183": "no",
        "184": "most",
        "185": "people",
        "186": "my",
        "187": "over",
        "188": "know",
        "189": "water",
        "190": "than",
        "191": "call",
        "192": "first",
        "193": "who",
        "194": "may",
        "195": "down",
        "196": "side",
        "197": "been",
        "198": "now",
        "199": "find",
        "200": "head",
        "201": "stand",
        "202": "own",
        "203": "page",
        "204": "should",
        "205": "country",
        "206": "found",
        "207": "answer",
        "208": "school",
        "209": "grow",
        "210": "study",
        "211": "still",
        "212": "learn",
        "213": "plant",
        "214": "cover",
        "215": "food",
        "216": "sun",
        "217": "four",
        "218": "between",
        "219": "state",
        "220": "keep",
        "221": "eye",
        "222": "never",
        "223": "last",
        "224": "let",
        "225": "thought",
        "226": "city",
        "227": "tree",
        "228": "cross",
        "229": "farm",
        "230": "hard",
        "231": "start",
        "232": "might",
        "233": "story",
        "234": "saw",
        "235": "far",
        "236": "sea",
        "237": "draw",
        "238": "left",
        "239": "late",
        "240": "run",
        "241": "don\u2019t",
        "242": "while",
        "243": "press",
        "244": "close",
        "245": "night",
        "246": "real",
        "247": "life",
        "248": "few",
        "249": "north",
        "250": "book",
        "251": "carry",
        "252": "took",
        "253": "science",
        "254": "eat",
        "255": "room",
        "256": "friend",
        "257": "began",
        "258": "idea",
        "259": "fish",
        "260": "mountain",
        "261": "stop",
        "262": "once",
        "263": "base",
        "264": "hear",
        "265": "horse",
        "266": "cut",
        "267": "sure",
        "268": "watch",
        "269": "color",
        "270": "face",
        "271": "wood",
        "272": "main",
        "273": "open",
        "274": "seem",
        "275": "together",
        "276": "next",
        "277": "white",
        "278": "children",
        "279": "begin",
        "280": "got",
        "281": "walk",
        "282": "example",
        "283": "ease",
        "284": "paper",
        "285": "group",
        "286": "always",
        "287": "music",
        "288": "those",
        "289": "both",
        "290": "mark",
        "291": "often",
        "292": "letter",
        "293": "until",
        "294": "mile",
        "295": "river",
        "296": "car",
        "297": "feet",
        "298": "care",
        "299": "second",
        "300": "enough",
        "301": "plain",
        "302": "girl",
        "303": "usual",
        "304": "young",
        "305": "ready",
        "306": "above",
        "307": "ever",
        "308": "red",
        "309": "list",
        "310": "though",
        "311": "feel",
        "312": "talk",
        "313": "bird",
        "314": "soon",
        "315": "body",
        "316": "dog",
        "317": "family",
        "318": "direct",
        "319": "pose",
        "320": "leave",
        "321": "song",
        "322": "measure",
        "323": "door",
        "324": "product",
        "325": "black",
        "326": "short",
        "327": "numeral",
        "328": "class",
        "329": "wind",
        "330": "question",
        "331": "happen",
        "332": "complete",
        "333": "ship",
        "334": "area",
        "335": "half",
        "336": "rock",
        "337": "order",
        "338": "fire",
        "339": "south",
        "340": "problem",
        "341": "piece",
        "342": "told",
        "343": "knew",
        "344": "pass",
        "345": "since",
        "346": "top",
        "347": "whole",
        "348": "king",
        "349": "street",
        "350": "inch",
        "351": "multiply",
        "352": "nothing",
        "353": "course",
        "354": "stay",
        "355": "wheel",
        "356": "full",
        "357": "force",
        "358": "blue",
        "359": "object",
        "360": "decide",
        "361": "surface",
        "362": "deep",
        "363": "moon",
        "364": "island",
        "365": "foot",
        "366": "system",
        "367": "busy",
        "368": "test",
        "369": "record",
        "370": "boat",
        "371": "common",
        "372": "gold",
        "373": "possible",
        "374": "plane",
        "375": "stead",
        "376": "dry",
        "377": "wonder",
        "378": "laugh",
        "379": "thousand",
        "380": "ago",
        "381": "ran",
        "382": "check",
        "383": "game",
        "384": "shape",
        "385": "equate",
        "386": "hot",
        "387": "miss",
        "388": "brought",
        "389": "heat",
        "390": "snow",
        "391": "tire",
        "392": "bring",
        "393": "yes",
        "394": "distant",
        "395": "fill",
        "396": "east",
        "397": "paint",
        "398": "language",
        "399": "among",
        "400": "unit",
        "401": "power",
        "402": "town",
        "403": "fine",
        "404": "certain",
        "405": "fly",
        "406": "fall",
        "407": "lead",
        "408": "cry",
        "409": "dark",
        "410": "machine",
        "411": "note",
        "412": "wait",
        "413": "plan",
        "414": "figure",
        "415": "star",
        "416": "box",
        "417": "noun",
        "418": "field",
        "419": "rest",
        "420": "correct",
        "421": "able",
        "422": "pound",
        "423": "done",
        "424": "beauty",
        "425": "drive",
        "426": "stood",
        "427": "contain",
        "428": "front",
        "429": "teach",
        "430": "week",
        "431": "final",
        "432": "gave",
        "433": "green",
        "434": "oh",
        "435": "quick",
        "436": "develop",
        "437": "ocean",
        "438": "warm",
        "439": "free",
        "440": "minute",
        "441": "strong",
        "442": "special",
        "443": "mind",
        "444": "behind",
        "445": "clear",
        "446": "tail",
        "447": "produce",
        "448": "fact",
        "449": "space",
        "450": "heard",
        "451": "best",
        "452": "hour",
        "453": "better",
        "454": "TRUE",
        "455": "during",
        "456": "hundred",
        "457": "five",
        "458": "remember",
        "459": "step",
        "460": "early",
        "461": "hold",
        "462": "west",
        "463": "ground",
        "464": "interest",
        "465": "reach",
        "466": "fast",
        "467": "verb",
        "468": "sing",
        "469": "listen",
        "470": "six",
        "471": "table",
        "472": "travel",
        "473": "less",
        "474": "morning",
        "475": "ten",
        "476": "simple",
        "477": "several",
        "478": "vowel",
        "479": "toward",
        "480": "war",
        "481": "lay",
        "482": "against",
        "483": "pattern",
        "484": "slow",
        "485": "center",
        "486": "love",
        "487": "person",
        "488": "money",
        "489": "serve",
        "490": "appear",
        "491": "road",
        "492": "map",
        "493": "rain",
        "494": "rule",
        "495": "govern",
        "496": "pull",
        "497": "cold",
        "498": "notice",
        "499": "voice",
        "500": "energy",
        "501": "hunt",
        "502": "probable",
        "503": "bed",
        "504": "brother",
        "505": "egg",
        "506": "ride",
        "507": "cell",
        "508": "believe",
        "509": "perhaps",
        "510": "pick",
        "511": "sudden",
        "512": "count",
        "513": "square",
        "514": "reason",
        "515": "length",
        "516": "represent",
        "517": "art",
        "518": "subject",
        "519": "region",
        "520": "size",
        "521": "vary",
        "522": "settle",
        "523": "speak",
        "524": "weight",
        "525": "general",
        "526": "ice",
        "527": "matter",
        "528": "circle",
        "529": "pair",
        "530": "include",
        "531": "divide",
        "532": "syllable",
        "533": "felt",
        "534": "grand",
        "535": "ball",
        "536": "yet",
        "537": "wave",
        "538": "drop",
        "539": "heart",
        "540": "am",
        "541": "present",
        "542": "heavy",
        "543": "dance",
        "544": "engine",
        "545": "position",
        "546": "arm",
        "547": "wide",
        "548": "sail",
        "549": "material",
        "550": "fraction",
        "551": "forest",
        "552": "sit",
        "553": "race",
        "554": "window",
        "555": "store",
        "556": "summer",
        "557": "train",
        "558": "sleep",
        "559": "prove",
        "560": "lone",
        "561": "leg",
        "562": "exercise",
        "563": "wall",
        "564": "catch",
        "565": "mount",
        "566": "wish",
        "567": "sky",
        "568": "board",
        "569": "joy",
        "570": "winter",
        "571": "sat",
        "572": "written",
        "573": "wild",
        "574": "instrument",
        "575": "kept",
        "576": "glass",
        "577": "grass",
        "578": "cow",
        "579": "job",
        "580": "edge",
        "581": "sign",
        "582": "visit",
        "583": "past",
        "584": "soft",
        "585": "fun",
        "586": "bright",
        "587": "gas",
        "588": "weather",
        "589": "month",
        "590": "million",
        "591": "bear",
        "592": "finish",
        "593": "happy",
        "594": "hope",
        "595": "flower",
        "596": "clothe",
        "597": "strange",
        "598": "gone",
        "599": "trade",
        "600": "melody",
        "601": "trip",
        "602": "office",
        "603": "receive",
        "604": "row",
        "605": "mouth",
        "606": "exact",
        "607": "symbol",
        "608": "die",
        "609": "least",
        "610": "trouble",
        "611": "shout",
        "612": "except",
        "613": "wrote",
        "614": "seed",
        "615": "tone",
        "616": "join",
        "617": "suggest",
        "618": "clean",
        "619": "break",
        "620": "lady",
        "621": "yard",
        "622": "rise",
        "623": "bad",
        "624": "blow",
        "625": "oil",
        "626": "blood",
        "627": "touch",
        "628": "grew",
        "629": "cent",
        "630": "mix",
        "631": "team",
        "632": "wire",
        "633": "cost",
        "634": "lost",
        "635": "brown",
        "636": "wear",
        "637": "garden",
        "638": "equal",
        "639": "sent",
        "640": "choose",
        "641": "fell",
        "642": "fit",
        "643": "flow",
        "644": "fair",
        "645": "bank",
        "646": "collect",
        "647": "save",
        "648": "control",
        "649": "decimal",
        "650": "ear",
        "651": "else",
        "652": "quite",
        "653": "broke",
        "654": "case",
        "655": "middle",
        "656": "kill",
        "657": "son",
        "658": "lake",
        "659": "moment",
        "660": "scale",
        "661": "loud",
        "662": "spring",
        "663": "observe",
        "664": "child",
        "665": "straight",
        "666": "consonant",
        "667": "nation",
        "668": "dictionary",
        "669": "milk",
        "670": "speed",
        "671": "method",
        "672": "organ",
        "673": "pay",
        "674": "age",
        "675": "section",
        "676": "dress",
        "677": "cloud",
        "678": "surprise",
        "679": "quiet",
        "680": "stone",
        "681": "tiny",
        "682": "climb",
        "683": "cool",
        "684": "design",
        "685": "poor",
        "686": "lot",
        "687": "experiment",
        "688": "bottom",
        "689": "key",
        "690": "iron",
        "691": "single",
        "692": "stick",
        "693": "flat",
        "694": "twenty",
        "695": "skin",
        "696": "smile",
        "697": "crease",
        "698": "hole",
        "699": "jump",
        "700": "baby",
        "701": "eight",
        "702": "village",
        "703": "meet",
        "704": "root",
        "705": "buy",
        "706": "raise",
        "707": "solve",
        "708": "metal",
        "709": "whether",
        "710": "push",
        "711": "seven",
        "712": "paragraph",
        "713": "third",
        "714": "shall",
        "715": "held",
        "716": "hair",
        "717": "describe",
        "718": "cook",
        "719": "floor",
        "720": "either",
        "721": "result",
        "722": "burn",
        "723": "hill",
        "724": "safe",
        "725": "cat",
        "726": "century",
        "727": "consider",
        "728": "type",
        "729": "law",
        "730": "bit",
        "731": "coast",
        "732": "copy",
        "733": "phrase",
        "734": "silent",
        "735": "tall",
        "736": "sand",
        "737": "soil",
        "738": "roll",
        "739": "temperature",
        "740": "finger",
        "741": "industry",
        "742": "value",
        "743": "fight",
        "744": "lie",
        "745": "beat",
        "746": "excite",
        "747": "natural",
        "748": "view",
        "749": "sense",
        "750": "capital",
        "751": "won\u2019t",
        "752": "chair",
        "753": "danger",
        "754": "fruit",
        "755": "rich",
        "756": "thick",
        "757": "soldier",
        "758": "process",
        "759": "operate",
        "760": "practice",
        "761": "separate",
        "762": "difficult",
        "763": "doctor",
        "764": "please",
        "765": "protect",
        "766": "noon",
        "767": "crop",
        "768": "modern",
        "769": "element",
        "770": "hit",
        "771": "student",
        "772": "corner",
        "773": "party",
        "774": "supply",
        "775": "whose",
        "776": "locate",
        "777": "ring",
        "778": "character",
        "779": "insect",
        "780": "caught",
        "781": "period",
        "782": "indicate",
        "783": "radio",
        "784": "spoke",
        "785": "atom",
        "786": "human",
        "787": "history",
        "788": "effect",
        "789": "electric",
        "790": "expect",
        "791": "bone",
        "792": "rail",
        "793": "imagine",
        "794": "provide",
        "795": "agree",
        "796": "thus",
        "797": "gentle",
        "798": "woman",
        "799": "captain",
        "800": "guess",
        "801": "necessary",
        "802": "sharp",
        "803": "wing",
        "804": "create",
        "805": "neighbor",
        "806": "wash",
        "807": "bat",
        "808": "rather",
        "809": "crowd",
        "810": "corn",
        "811": "compare",
        "812": "poem",
        "813": "string",
        "814": "bell",
        "815": "depend",
        "816": "meat",
        "817": "rub",
        "818": "tube",
        "819": "famous",
        "820": "dollar",
        "821": "stream",
        "822": "fear",
        "823": "sight",
        "824": "thin",
        "825": "triangle",
        "826": "planet",
        "827": "hurry",
        "828": "chief",
        "829": "colony",
        "830": "clock",
        "831": "mine",
        "832": "tie",
        "833": "enter",
        "834": "major",
        "835": "fresh",
        "836": "search",
        "837": "send",
        "838": "yellow",
        "839": "gun",
        "840": "allow",
        "841": "print",
        "842": "dead",
        "843": "spot",
        "844": "desert",
        "845": "suit",
        "846": "current",
        "847": "lift",
        "848": "rose",
        "849": "arrive",
        "850": "master",
        "851": "track",
        "852": "parent",
        "853": "shore",
        "854": "division",
        "855": "sheet",
        "856": "substance",
        "857": "favor",
        "858": "connect",
        "859": "post",
        "860": "spend",
        "861": "chord",
        "862": "fat",
        "863": "glad",
        "864": "original",
        "865": "share",
        "866": "station",
        "867": "dad",
        "868": "bread",
        "869": "charge",
        "870": "proper",
        "871": "bar",
        "872": "offer",
        "873": "segment",
        "874": "slave",
        "875": "duck",
        "876": "instant",
        "877": "market",
        "878": "degree",
        "879": "populate",
        "880": "chick",
        "881": "dear",
        "882": "enemy",
        "883": "reply",
        "884": "drink",
        "885": "occur",
        "886": "support",
        "887": "speech",
        "888": "nature",
        "889": "range",
        "890": "steam",
        "891": "motion",
        "892": "path",
        "893": "liquid",
        "894": "log",
        "895": "meant",
        "896": "quotient",
        "897": "teeth",
        "898": "shell",
        "899": "neck",
        "900": "oxygen",
        "901": "sugar",
        "902": "death",
        "903": "pretty",
        "904": "skill",
        "905": "women",
        "906": "season",
        "907": "solution",
        "908": "magnet",
        "909": "silver",
        "910": "thank",
        "911": "branch",
        "912": "match",
        "913": "suffix",
        "914": "especially",
        "915": "fig",
        "916": "afraid",
        "917": "huge",
        "918": "sister",
        "919": "steel",
        "920": "discuss",
        "921": "forward",
        "922": "similar",
        "923": "guide",
        "924": "experience",
        "925": "score",
        "926": "apple",
        "927": "bought",
        "928": "led",
        "929": "pitch",
        "930": "coat",
        "931": "mass",
        "932": "card",
        "933": "band",
        "934": "rope",
        "935": "slip",
        "936": "win",
        "937": "dream",
        "938": "evening",
        "939": "condition",
        "940": "feed",
        "941": "tool",
        "942": "total",
        "943": "basic",
        "944": "smell",
        "945": "valley",
        "946": "nor",
        "947": "double",
        "948": "seat",
        "949": "continue",
        "950": "block",
        "951": "chart",
        "952": "hat",
        "953": "sell",
        "954": "success",
        "955": "company",
        "956": "subtract",
        "957": "event",
        "958": "particular",
        "959": "deal",
        "960": "swim",
        "961": "term",
        "962": "opposite",
        "963": "wife",
        "964": "shoe",
        "965": "shoulder",
        "966": "spread",
        "967": "arrange",
        "968": "camp",
        "969": "invent",
        "970": "cotton",
        "971": "born",
        "972": "determine",
        "973": "quart",
        "974": "nine",
        "975": "truck",
        "976": "noise",
        "977": "level",
        "978": "chance",
        "979": "gather",
        "980": "shop",
        "981": "stretch",
        "982": "throw",
        "983": "shine",
        "984": "property",
        "985": "column",
        "986": "molecule",
        "987": "select",
        "988": "wrong",
        "989": "gray",
        "990": "repeat",
        "991": "require",
        "992": "broad",
        "993": "prepare",
        "994": "salt",
        "995": "nose",
        "996": "plural",
        "997": "anger",
        "998": "claim",
        "999": "continent",
        "1000": NaN,
        "1001": NaN
    }
}